Metadata-Version: 2.1
Name: catalog_builder
Version: 0.8
Summary: Data Catalogs Made Easy
Download-URL: https://github.com/unytics/catalog_builder/archive/refs/tags/v0.8.tar.gz
Author: Unytics
Author-email: paul.marcombes@unytics.io
Classifier: Programming Language :: Python :: 3
Classifier: License :: OSI Approved :: MIT License
Classifier: Operating System :: OS Independent
Requires-Python: >=3.6
License-File: LICENSE
Requires-Dist: mkdocs-material
Requires-Dist: mkdocs-awesome-pages-plugin
Requires-Dist: click
Requires-Dist: click-help-colors
Requires-Dist: pyarrow
Requires-Dist: pandas
Requires-Dist: requests
